<?xml version="1.0" encoding="UTF-8"?><!--Copyright 2015 Bluetooth SIG, Inc. All rights reserved.-->
<Characteristic xmlns:xsi="http://www.w3.org/2001/XMLSchema-instance" name="Altitude" approved="Yes"
    last-modified="2015-05-19" type="org.bluetooth.characteristic.altitude" uuid="2AB3"
    xsi:noNamespaceSchemaLocation="http://schemas.bluetooth.org/Documents/characteristic.xsd">
    <InformativeText>
        <Abstract>
            The Altitude characteristic describes the altitude of the device.
        </Abstract>
    </InformativeText>
    <Value>
        <Field name="Altitude">
            <Requirement>Mandatory</Requirement>
            <Format>uint16</Format>
        </Field>
    </Value>
</Characteristic>
